combine_csv/__init__.py
combine_csv/merge.py
combine_csv/pivot.py
combine_csv/sas.py
combine_csv/split.py
combine_csv-3.0.0.dist-info/LICENSE
combine_csv-3.0.0.dist-info/METADATA
combine_csv-3.0.0.dist-info/WHEEL
combine_csv-3.0.0.dist-info/entry_points.txt
combine_csv-3.0.0.dist-info/top_level.txt
combine_csv-3.0.0.dist-info/RECORD
