Metadata-Version: 2.1
Name: combine-csv
Version: 3.0.0
Summary: A small tool to merge CSV/TSV files
Author: Raynald de Lahondès
Project-URL: Homepage, https://github.com/gmtsciencedev/combine_csv
Project-URL: Bug Tracker, https://github.com/gmtsciencedev/combine_csv/issues
Project-URL: Documentation, https://combine_csv.readthedocs.io/
Classifier: Programming Language :: Python :: 3
Classifier: License :: OSI Approved :: BSD License
Classifier: Development Status :: 4 - Beta
Classifier: Operating System :: OS Independent
Requires-Python: >=3.6
License-File: LICENSE
Requires-Dist: pandas
Requires-Dist: pyreadstat
